ml_dash/__init__.py
ml_dash/auth/__init__.py
ml_dash/auth/constants.py
ml_dash/auth/device_flow.py
ml_dash/auth/device_secret.py
ml_dash/auth/exceptions.py
ml_dash/auth/token_storage.py
ml_dash/auto_start.py
ml_dash/cli.py
ml_dash/cli_commands/__init__.py
ml_dash/cli_commands/download.py
ml_dash/cli_commands/list.py
ml_dash/cli_commands/login.py
ml_dash/cli_commands/logout.py
ml_dash/cli_commands/upload.py
ml_dash/client.py
ml_dash/config.py
ml_dash/experiment.py
ml_dash/files.py
ml_dash/log.py
ml_dash/metric.py
ml_dash/params.py
ml_dash/py.typed
ml_dash/remote_auto_start.py
ml_dash/storage.py
ml_dash-0.6.1.dist-info/WHEEL
ml_dash-0.6.1.dist-info/entry_points.txt
ml_dash-0.6.1.dist-info/METADATA
ml_dash-0.6.1.dist-info/RECORD
