Metadata-Version: 2.3
Name: ml-dash
Version: 0.6.1
Summary: ML experiment tracking and data storage
Keywords: machine-learning,experiment-tracking,mlops,data-storage
Author: Ge Yang, Tom Tao
License: MIT License
Classifier: Development Status :: 4 - Beta
Classifier: Intended Audience :: Developers
Classifier: Intended Audience :: Science/Research
Classifier: License :: OSI Approved :: MIT License
Classifier: Programming Language :: Python :: 3
Classifier: Programming Language :: Python :: 3.9
Classifier: Programming Language :: Python :: 3.10
Classifier: Programming Language :: Python :: 3.11
Classifier: Programming Language :: Python :: 3.12
Classifier: Programming Language :: Python :: 3.13
Classifier: Topic :: Scientific/Engineering :: Artificial Intelligence
Requires-Dist: httpx>=0.27.0
Requires-Dist: pyjwt>=2.8.0
Requires-Dist: imageio>=2.31.0
Requires-Dist: imageio-ffmpeg>=0.4.9
Requires-Dist: scikit-image>=0.21.0
Requires-Dist: rich>=13.0.0
Requires-Dist: cryptography>=42.0.0
Requires-Dist: keyring>=25.0.0 ; extra == 'auth'
Requires-Dist: qrcode>=8.0.0 ; extra == 'auth'
Requires-Dist: pytest>=8.0.0 ; extra == 'dev'
Requires-Dist: pytest-asyncio>=0.23.0 ; extra == 'dev'
Requires-Dist: sphinx>=7.2.0 ; extra == 'dev'
Requires-Dist: furo>=2024.0.0 ; extra == 'dev'
Requires-Dist: sphinx-autodoc-typehints>=2.0.0 ; extra == 'dev'
Requires-Dist: sphinx-autobuild>=2024.0.0 ; extra == 'dev'
Requires-Dist: sphinx-copybutton>=0.5.0 ; extra == 'dev'
Requires-Dist: sphinx-design>=0.5.0 ; extra == 'dev'
Requires-Dist: sphinx-tabs>=3.4.0 ; extra == 'dev'
Requires-Dist: sphinxcontrib-mermaid>=0.9.0 ; extra == 'dev'
Requires-Dist: sphinxext-opengraph>=0.9.0 ; extra == 'dev'
Requires-Dist: myst-parser>=2.0.0 ; extra == 'dev'
Requires-Dist: linkify-it-py>=2.0.0 ; extra == 'dev'
Requires-Dist: ruff>=0.3.0 ; extra == 'dev'
Requires-Dist: mypy>=1.9.0 ; extra == 'dev'
Requires-Python: >=3.9
Provides-Extra: auth
Provides-Extra: dev
